{
    "TravelDestinations": [
      {
            "id" : "01",
            "country": "Spain",
            "flag": "🇪🇸",
            "destinations": [
                {
                    "id" : "06",
                    "city": "Barcelona",
                    "type": "Coastal City",
                    "popular": "Sagrada Familia",
                    "image" : "Barcelona.webp"
                },
                {
                    "id" : "07",
                    "city": "Madrid",
                    "type": "Capital City",
                    "popular": "museums",
                    "image" : "madrid.jpg"
                },
                {
                    "id" : "08",
                    "city": "Valencia",
                    "type": "Coastal City",
                    "popular": "Futuristic Architecture ",
                    "image" : "valencia.jpg"
                }
            ]
        },
        {
            "id" : "02",
            "country": "Italy",
            "flag": "🇮🇹",
            "destinations": [
                {
                    "id" : "09",
                    "city": "Rome",
                    "type": "Capital City",
                    "popular": "Colosseum",
                    "image" : "rome.webp"
                },
                {
                    "id" : "11",
                    "city": "Venice",
                    "type":"Coastal City",
                    "popular": "Canals",
                    "image" : "venice.jpg"
                },
                {
                    "id" : "10",
                    "city": "Florence",
                    "type": "City Break",
                    "popular": "Renaissance Art",
                    "image" : "florence.avif"
                }
            ]
        },
        {
            "id" : "03",
            "country": "France",
            "flag": "🇫🇷",
            "destinations": [
                {
                    "id" : "12",
                    "city": "Paris",
                    "type": "City Break",
                    "popular": "Eiffel Tower",
                    "image" : "paris.webp"
                },
                {
                    "id" : "13",
                    "city": "Bordeaux",
                    "type":"City Break",
                    "popular": "Wine",
                    "image" : "bordeaux.jpg"
                },
                {
                    "id" : "14",
                    "city": "Marseille",
                    "type": "Port City",
                    "popular": "Diverse cusine",
                    "image" : "marseille.jpg"
                }
            ]
        },
        {
            "id" : "04",
            "country": "United States of America",
            "flag": "🇺🇸",
            "destinations": [
                {
                    "id" : "15",
                    "city": "New York",
                    "type": "City Break",
                    "popular": "Statue of Liberty",
                    "image" : "newyork.jpg"
                },
                {
                    "id" : "16",
                    "city": "Miami",
                    "type":"Coastal City",
                    "popular": "Miami Beach",
                    "image" : "miami.webp"
                },
                {
                    "id" : "17",
                    "city": "Los Angeles",
                    "type": "Coastal City",
                    "popular" : "Hollywood",
                    "image" : "losangeles.jpeg"
                    
                }
            ]
        }
    ]
}